Metadata-Version: 2.1
Name: atlascloud
Version: 0.1
Requires-Dist: openai
